redis_flask/__init__.py
redis_flask-0.0.2.dist-info/METADATA
redis_flask-0.0.2.dist-info/WHEEL
redis_flask-0.0.2.dist-info/RECORD
