Metadata-Version: 2.1
Name: redis_flask
Version: 0.0.2
Summary: Redis extension for Flask app
Author: Robotz213
Author-email: nicholas@robotz.dev
Requires-Python: >=3.11,<4.0
Classifier: Programming Language :: Python :: 3
Classifier: Programming Language :: Python :: 3.11
Classifier: Programming Language :: Python :: 3.12
Classifier: Programming Language :: Python :: 3.13
Requires-Dist: Flask (>=3.1.0,<4.0.0)
Requires-Dist: redis (>=5.2.0,<6.0.0)
